ov5642_v3.srcs/sources_1/bd/design_1/ipshared/user.org/ov5642_capture_v4_v1_0/ov5642_capture_v4.v
//`timescale 1ns / 1ns
//////////////////////////////////////////////////////////////////////////////////
// Company: 
// Engineer: 
// 
// Create Date: 25.11.2015 17:00:47
// Design Name: 
// Module Name: ov5642-capture
// Project Name: 
// Target Devices: 
// Tool Versions: 
// Description: 
// 
// Dependencies: 
// 
// Revision:
// Revision 0.01 - File Created
// Additional Comments:
// 
//////////////////////////////////////////////////////////////////////////////////


module ov5642_capture_v4(input [7:0]cam_data,
    input href,
    input vsync,
    input pclk,
    input reset_n,
//    output reg end_of_line,
    output reg [16:0]address,
    output [7:0]pix_data,
    output reg write_enable
    );
    
reg [7:0]tmp_data;
reg [8:0]col_counter;

initial begin
    address <= 17'd0;
    tmp_data <= 8'd0;
    write_enable <= 1'b0;
//    col_counter <= 9'd0;
//    end_of_line <= 1'b0;
end    

//data input to buffer 
always @(posedge pclk or negedge reset_n) begin
    if (reset_n == 1'b0) begin
        tmp_data <= 8'd0;
    end
    else begin
        if (vsync == 1'b1) begin
            tmp_data <= 8'd0;
        end
        else if (href == 1'b1) begin //data is valid when href is high
                                     //2 bytes per pixel
            if (pix_counter == 1'b0) begin 
                //first byte (YYYYYYYY)
                tmp_data <= cam_data;
            end  
            //from second byte (UUUUUUUU or VVVVVVVV) 
        end
    end    
end


assign pix_data = tmp_data[7:0];

// input pixel byte counter
reg pix_counter;
always @(posedge pclk or negedge reset_n) begin
    if(reset_n == 1'b0) begin
        pix_counter <= 1'b0;
    end
    else begin
        if(vsync == 1'b1) begin
            pix_counter <= 1'b0;
        end
        else if (href == 1'b1) begin
            pix_counter <= pix_counter + 1'b1;
//            col_counter <= col_counter + 1'b1;
        end
    end
end

//always @(posedge pclk or negedge reset_n) begin
//    if(reset_n == 1'b0) begin
//        col_counter <= 9'd0;
//    end
//    else if (col_counter == 9'd319) begin
//        end_of_line <= 1'b1;
//        col_counter <= 9'd0;
//    end
//    else begin
//        end_of_line <= 1'b0;
//    end
//end
    
// RAM address generation 
always @(posedge pclk or negedge reset_n) begin
    if(reset_n == 1'b0) begin
        address <= 17'd0;
    end
    else if(vsync == 1'b1 ) begin
        address <= 17'd0;
    end
    else if (write_enable == 1'b1) begin
        address <= address + 1'b1;
    end
end

// Write enable
always @(negedge pclk or negedge reset_n) begin
    if(reset_n == 1'b0) begin
        write_enable <= 1'b0;
    end
    else begin
        if (pix_counter == 1'b1) begin
            write_enable <= 1'b1;
        end
        else begin
            write_enable <= 1'b0;
        end
    end
end



endmodule

custom_ip/ov5642_capture_v4/testbench/tb_ov5642_capture_v4.v
`timescale 1 ns / 1 ns

module tb_ov5642_capture_v4();

reg [3:0]i;

reg [7:0]cam_data;
reg href;
reg vsync;
reg pclk;
reg reset_n;

wire [16:0]address;
wire [7:0]pix_data;
wire write_enable;

ov5642_capture_v4 ov5642(.cam_data(cam_data),
                         .href(href),
                         .vsync(vsync),
                         .pclk(pclk),
                         .reset_n(reset_n),
                         .address(address),
                         .pix_data(pix_data),
                         .write_enable(write_enable));

initial begin
  pclk = 0;
  href = 0;
  vsync = 0;
  reset_n = 0;
  cam_data = 0;
  forever #5 pclk = !pclk;
  
end

initial begin
  $dumpfile ("tb_ov5642_capture_v4.vcd"); 
  $dumpvars;//(tb_dvs_cdma_v1); 
  #15 reset_n = 1;
  #1  vsync = 1;
  #9  vsync = 0;
  #10 href  = 1;
  for (i = 0; i < 4; i = i + 1) begin
    #10 cam_data = 255;
    #10 cam_data = 10;
    #10 cam_data = 255;
    #10 cam_data = 20;
    #10 cam_data = 255;
    #10 cam_data = 30;
  end
  #10 href = 0;
  #10 $finish;
end


endmodule

custom_ip/ov5642_capture_v4/testbench/tb_ov5642_capture_v4.vcd
$date
	Mon Feb 22 18:48:48 2016
$end
$version
	Icarus Verilog
$end
$timescale
	1ns
$end
$scope module tb_ov5642_capture_v4 $end
$var wire 1 ! write_enable $end
$var wire 8 " pix_data [7:0] $end
$var wire 17 # address [16:0] $end
$var reg 8 $ cam_data [7:0] $end
$var reg 1 % href $end
$var reg 4 & i [3:0] $end
$var reg 1 ' pclk $end
$var reg 1 ( reset_n $end
$var reg 1 ) vsync $end
$scope module ov5642 $end
$var wire 8 * cam_data [7:0] $end
$var wire 1 % href $end
$var wire 1 ' pclk $end
$var wire 8 + pix_data [7:0] $end
$var wire 1 ( reset_n $end
$var wire 1 ) vsync $end
$var reg 17 , address [16:0] $end
$var reg 1 - pix_counter $end
$var reg 8 . tmp_data [7:0] $end
$var reg 1 ! write_enable $end
$upscope $end
$upscope $end
$enddefinitions $end
#0
$dumpvars
b0 .
0-
b0 ,
b0 +
b0 *
0)
0(
0'
bx &
0%
b0 $
b0 #
b0 "
0!
$end
#5
1'
#10
0'
#15
1'
1(
#16
1)
#20
0'
#25
1'
0)
#30
0'
#35
1-
1'
b0 &
1%
#40
1!
0'
#45
b1 #
b1 ,
0-
1'
b11111111 $
b11111111 *
#50
0!
0'
#55
b1010 "
b1010 +
b1010 .
1-
1'
b1010 $
b1010 *
#60
1!
0'
#65
b10 #
b10 ,
0-
1'
b11111111 $
b11111111 *
#70
0!
0'
#75
b10100 "
b10100 +
b10100 .
1-
1'
b10100 $
b10100 *
#80
1!
0'
#85
b11 #
b11 ,
0-
1'
b11111111 $
b11111111 *
#90
0!
0'
#95
b11110 "
b11110 +
b11110 .
1-
1'
b1 &
b11110 $
b11110 *
#100
1!
0'
#105
b100 #
b100 ,
0-
1'
b11111111 $
b11111111 *
#110
0!
0'
#115
b1010 "
b1010 +
b1010 .
1-
1'
b1010 $
b1010 *
#120
1!
0'
#125
b101 #
b101 ,
0-
1'
b11111111 $
b11111111 *
#130
0!
0'
#135
b10100 "
b10100 +
b10100 .
1-
1'
b10100 $
b10100 *
#140
1!
0'
#145
b110 #
b110 ,
0-
1'
b11111111 $
b11111111 *
#150
0!
0'
#155
b11110 "
b11110 +
b11110 .
1-
1'
b10 &
b11110 $
b11110 *
#160
1!
0'
#165
b111 #
b111 ,
0-
1'
b11111111 $
b11111111 *
#170
0!
0'
#175
b1010 "
b1010 +
b1010 .
1-
1'
b1010 $
b1010 *
#180
1!
0'
#185
b1000 #
b1000 ,
0-
1'
b11111111 $
b11111111 *
#190
0!
0'
#195
b10100 "
b10100 +
b10100 .
1-
1'
b10100 $
b10100 *
#200
1!
0'
#205
b1001 #
b1001 ,
0-
1'
b11111111 $
b11111111 *
#210
0!
0'
#215
b11110 "
b11110 +
b11110 .
1-
1'
b11 &
b11110 $
b11110 *
#220
1!
0'
#225
b1010 #
b1010 ,
0-
1'
b11111111 $
b11111111 *
#230
0!
0'
#235
b1010 "
b1010 +
b1010 .
1-
1'
b1010 $
b1010 *
#240
1!
0'
#245
b1011 #
b1011 ,
0-
1'
b11111111 $
b11111111 *
#250
0!
0'
#255
b10100 "
b10100 +
b10100 .
1-
1'
b10100 $
b10100 *
#260
1!
0'
#265
b1100 #
b1100 ,
0-
1'
b11111111 $
b11111111 *
#270
0!
0'
#275
b11110 "
b11110 +
b11110 .
1-
1'
b100 &
b11110 $
b11110 *
#280
1!
0'
#285
b1101 #
b1101 ,
1'
0%
#290
0'
#295
b1110 #
b1110 ,
1'
