custom_ip/dvs_cdma_v1/dvs_cdma_v1.v
/**********************************************************************

Extracting a 128x128 image from a 320x240 frame

   0      96      224     320
   /----------------------/- - -  0
   /      :       :       /
   /      :_______:_ _ _ _/_ _ _  56
   /      |       |       /
   /      |       |       /
   /      |_______|_ _ _ _/_ _ _  184
   /                      /
   /                      /
   /----------------------/- - -  240
   
   
We read and compare with a reference, one line at a time.
Lines are transfered through a buffer, thus the BRAM controller
Lines are requested with a pulse through read_new_line
A write line request is indicated with a pulse on write_new_line

**********************************************************************/



module dvs_cdma_v1(
// camera input
                    input  pclk,
                    input  vsync,
                    input  href,
                    input  [7:0] pix_data,
                    input  write_enable_in,
// threshold value
                    input  [7:0] threshold,
// signal the PS a new frame has just started (reset PS address/change buffer)
                    output new_frame, 
// signal the PS to issue new line FROM DDR <-
                    output reg read_new_line, 
// signal the PS to transfer new line TO DDR ->
                    output reg write_new_line,
// bram interface
                    output reg [16:0] bram_addr,
                    output bram_clk,
                    output reg [31:0] bram_wrdata,
                    input  [31:0] bram_rddata,
                    output bram_en,
                    output bram_rst,
                    output [3:0] bram_we,
// block reset
                    input  reset
                  );


reg write_enable_out;
reg [8:0] column_counter;
reg [7:0] line_counter;
reg pix_per_pack_count;

assign new_frame = vsync;
assign bram_we  = {write_enable_out, write_enable_out, write_enable_out};
assign bram_rst = reset;
assign bram_en  = !reset;
assign bram_clk = pclk;


// read new line flag
always @(posedge pclk or negedge reset) begin
  if (reset == 1'b1) begin
    read_new_line <= 1'b0;
  end
  else begin
        //after writing (col_count = 224), read next
    if( column_counter == 9'd320 || 
       (column_counter == 9'd0 && line_counter == 8'd0 && new_frame == 1'b1)) begin //first pixel, read first line

      read_new_line <= 1'b1;
    end
    else begin
      read_new_line <= 1'b0;
    end
  end
end


// write results flag
always @(posedge pclk or negedge reset) begin
  if (reset == 1'b1) begin
    write_new_line <= 1'b0; 
  end
  else begin
    if( column_counter == 8'd224 ) begin
      write_new_line <= 1'b1;
    end
    else begin
      write_new_line <= 1'b0;
    end
  end
  
end

// count lines
always @(posedge pclk or negedge reset) begin
  if(reset == 1'b1) begin
    line_counter <= 8'd0;
  end
  else begin
    if (vsync == 1'b0) begin
      line_counter <= 8'd0;
    end
    else begin
      if (column_counter >= 9'd319) begin
        line_counter <= line_counter + 8'd1;
      end
    end
  end
end

//                | | |
// count columns  v v v is this possible?
always @(negedge write_enable_in or negedge reset) begin

  if(reset == 1'b1) begin
    column_counter <= 9'd0;
  end
  else begin
    if ( vsync == 1'b1 || href  == 1'b0 ) begin
      column_counter <= 9'd0;
    end
    else begin
      column_counter <= column_counter + 9'd1;
    end
  end
  
end

// received pixels count
always @(posedge write_enable_in or negedge reset) begin

  if(reset == 1'b1) begin
    pix_per_pack_count <= 1'b0;
  end
  else begin
    if (href == 1'b1 && column_counter > 9'd0) begin
      pix_per_pack_count <= pix_per_pack_count + 1'b1;
    end
    else begin
      pix_per_pack_count <= 1'b0;
    end
  end
  
end


/* ************************************************************ 
   
   BLOCK RAM CONTROL
      output reg [16:0] bram_addr,
      output bram_clk,               <- wire
      output reg [31:0] bram_wrdata,
      input  [31:0] bram_rddata,
      output bram_en,                <- wire
      output bram_rst,               <- wire
      output [3:0] bram_we,
      
   ************************************************************ */

// bram address
always @(posedge pclk or negedge reset) begin
  if ( reset == 1'b1 ) begin
    bram_addr <= 17'd0;
  end
  else begin
    if ( pix_per_pack_count == 1'b1 &&
         column_counter >= 9'd96) begin
         
      bram_addr <= bram_addr + 17'd1;
    end
    
    if ( column_counter == 9'd224 ) begin
      bram_addr <= 17'd0;
    end
    
  end
end



// read & write data register
/*
     -------------------------------------------------------------------
 var |   ref0   | colour0 |  pixel0   |   ref1   | colour0 |  pixel0   |
     -------------------------------------------------------------------
 bit |  31 : 24 |  23:22  |  21 : 16  |  15 : 8  |  7 : 6  |   5 : 0   |
     -------------------------------------------------------------------
*/
always @(posedge pclk or negedge reset) begin
  if ( reset == 1'b1 ) begin
    bram_wrdata <= 31'd0;
  end
  else begin
    if ( pix_per_pack_count == 1'b0 &&
         write_enable_in == 1'b1 ) begin
      
      bram_wrdata[21:16] <= pix_data[7:2];
      
      if( ($signed({1'b0, pix_data[7:0]}) - $signed({1'b0, bram_rddata[31:24]})) > $signed({1'b0, threshold[7:0]}) ) begin
        bram_wrdata[31:24] <= pix_data[7:0];
        bram_wrdata[23:22] <= 2'b01; // green -- positive
      end
      else begin 
        if( ($signed({1'b0, pix_data[7:0]}) - $signed({1'b0, bram_rddata[31:24]})) < -$signed({1'b0, threshold[7:0]}) ) begin
          bram_wrdata[31:24] <= pix_data[7:0];
          bram_wrdata[23:22] <= 2'b10; // red -- negative
        end
        else begin
          bram_wrdata[23:22] <= 2'b00;
        end
      end
    end
    else begin if ( pix_per_pack_count == 1'b1 &&
                    write_enable_in == 1'b1 ) begin
      
        bram_wrdata[5:0] <= pix_data[7:2];
        
        if( ($signed({1'b0, pix_data[7:0]}) - $signed({1'b0, bram_rddata[15:8]})) > $signed({1'b0, threshold[7:0]}) ) begin
          bram_wrdata[15:8] <= pix_data[7:0];
          bram_wrdata[7:6] <= 2'b01; // green -- positive
        end
        else begin 
          if( ($signed({1'b0, pix_data[7:0]}) - $signed({1'b0, bram_rddata[15:8]})) < -$signed({1'b0, threshold[7:0]}) ) begin
            bram_wrdata[15:8] <= pix_data[7:0];
            bram_wrdata[7:6] <= 2'b10; // red -- negative
          end
          else begin
            bram_wrdata[7:6] <= 2'b00;
          end
        end
      end
      
    end
  end
  
end

//write enable out
always @(posedge pclk or negedge reset) begin
  if ( reset == 1'b1 ) begin
    write_enable_out <= 1'b0;
  end
  else begin
    if ( pix_per_pack_count == 1'b1 &&
         write_enable_in == 1'b0 ) begin

        write_enable_out <= 1'b1;
    end
    else begin
        write_enable_out <= 1'b0;
    end
  end
end

//waddress out
always @(posedge pclk or negedge reset) begin
  if ( reset == 1'b1 ) begin
    bram_addr <= 17'd0;
  end
  else begin
    if ( read_new_line == 1'b1 ) begin

      bram_addr <= 17'd0;
    end
    else begin 
      if ( write_enable_out == 1'b1 ) begin

        bram_addr <= bram_addr + 17'd1;
      end
    end
  end
end

endmodule

custom_ip/dvs_cdma_v1/testbench/tb_dvs_cdma_v1.v
`timescale 1 ns / 1 ns

module tb_dvs_cdma_v1();

reg [3:0] i;

reg pclk;
reg vsync;
reg href;
reg [7:0]pix_data;
reg write_enable_in;
reg [7:0]threshold;
reg [31:0]bram_rddata;
reg reset;

wire new_frame; 
wire read_new_line; 
wire write_new_line;
wire [16:0] bram_addr;
wire bram_clk;
wire [31:0] bram_wrdata;
wire bram_en;
wire bram_rst;
wire [3:0] bram_we;



dvs_cdma_v1 dvs_cdma(.pclk (pclk),
                     .vsync (vsync),
                     .href (href),
                     .pix_data (pix_data),
                     .write_enable_in (write_enable_in),
                     .threshold (threshold),
                     .new_frame (new_frame), 
                     .read_new_line (read_new_line), 
                     .write_new_line (write_new_line),
                     .bram_addr (bram_addr),
                     .bram_clk (bram_clk),
                     .bram_wrdata (bram_wrdata),
                     .bram_rddata (bram_rddata),
                     .bram_en (bram_en),
                     .bram_rst (bram_rst),
                     .bram_we (bram_we),
                     .reset (reset)
                    );


initial begin
  pclk = 1'b1;
  forever #5 pclk = !pclk;
end

initial  begin
  $dumpfile ("vcd_dvs_cdma.vcd"); 
  $dumpvars;//(tb_dvs_cdma_v1); 
  
  vsync = 1'b0;
  href = 1'b0;
  pix_data = 8'd0;
  write_enable_in = 1'b0;
  threshold = 8'd12;
  bram_rddata = 32'd0;
  reset = 1'b1;
  
  #10 reset = 1'b0;
  
  #1 pix_data = 8'd10;
  
  #9 vsync = 1'b1;
  
  #10 vsync = 1'b0;
  
  #10 href = 1'b1;
  #5
  for(i=4'd0; i < 4'd4; i = i + 4'b1) begin
    bram_rddata = 32'd0;

    #5 pix_data = 8'd10;

    #5 write_enable_in = 1'b1;
    #10 write_enable_in = 1'b0;
    

    #5 pix_data = 8'd20;

    #5 write_enable_in = 1'b1;
    #10 write_enable_in = 1'b0;


    bram_rddata = 32'h00002800;


    #5 pix_data = 8'd10;

    #5 write_enable_in = 1'b1;
    #10 write_enable_in = 1'b0;

    #5 pix_data = 8'd20;

    #5 write_enable_in = 1'b1;
    #10 write_enable_in = 1'b0;
  end
  #40 $finish;
end 


endmodule

custom_ip/dvs_cdma_v1/testbench/vcd_dvs_cdma.vcd
$date
	Mon Feb 22 19:35:29 2016
$end
$version
	Icarus Verilog
$end
$timescale
	1ns
$end
$scope module tb_dvs_cdma_v1 $end
$var wire 1 ! write_new_line $end
$var wire 1 " read_new_line $end
$var wire 1 # new_frame $end
$var wire 32 $ bram_wrdata [31:0] $end
$var wire 4 % bram_we [3:0] $end
$var wire 1 & bram_rst $end
$var wire 1 ' bram_en $end
$var wire 1 ( bram_clk $end
$var wire 17 ) bram_addr [16:0] $end
$var reg 32 * bram_rddata [31:0] $end
$var reg 1 + href $end
$var reg 4 , i [3:0] $end
$var reg 1 - pclk $end
$var reg 8 . pix_data [7:0] $end
$var reg 1 / reset $end
$var reg 8 0 threshold [7:0] $end
$var reg 1 1 vsync $end
$var reg 1 2 write_enable_in $end
$scope module dvs_cdma $end
$var wire 1 ( bram_clk $end
$var wire 32 3 bram_rddata [31:0] $end
$var wire 1 & bram_rst $end
$var wire 1 + href $end
$var wire 1 # new_frame $end
$var wire 1 - pclk $end
$var wire 8 4 pix_data [7:0] $end
$var wire 1 / reset $end
$var wire 8 5 threshold [7:0] $end
$var wire 1 1 vsync $end
$var wire 1 2 write_enable_in $end
$var wire 4 6 bram_we [3:0] $end
$var wire 1 ' bram_en $end
$var reg 17 7 bram_addr [16:0] $end
$var reg 32 8 bram_wrdata [31:0] $end
$var reg 9 9 column_counter [8:0] $end
$var reg 8 : line_counter [7:0] $end
$var reg 1 ; pix_per_pack_count $end
$var reg 1 " read_new_line $end
$var reg 1 < write_enable_out $end
$var reg 1 ! write_new_line $end
$upscope $end
$upscope $end
$enddefinitions $end
#0
$dumpvars
0<
x;
b0 :
b0 9
b0 8
b0 7
b0 6
b1100 5
b0 4
b0 3
02
01
b1100 0
1/
b0 .
1-
bx ,
0+
b0 *
b0 )
1(
0'
1&
b0 %
b0 $
0#
0"
0!
$end
#5
0(
0-
#10
0;
1(
1-
0&
1'
0/
#11
b1010 .
b1010 4
#15
0(
0-
#20
1"
1(
1-
1#
11
#25
0(
0-
#30
0"
1(
1-
0#
01
#35
0(
0-
#40
1(
1-
1+
#45
0(
0-
b0 ,
#50
1(
1-
#55
0(
0-
12
#60
b100000000000000000 $
b100000000000000000 8
1(
1-
#65
b1 9
0(
0-
02
#70
1(
1-
b10100 .
b10100 4
#75
1;
0(
0-
12
#80
b100001010001000101 $
b100001010001000101 8
1(
1-
#85
b10 9
0(
0-
b10100000000000 *
b10100000000000 3
02
#90
b111 %
b111 6
1<
1(
1-
b1010 .
b1010 4
#95
0;
0(
0-
12
#100
b0 %
b0 6
0<
b1 )
b1 7
1(
1-
#105
b11 9
0(
0-
02
#110
1(
1-
b10100 .
b10100 4
#115
1;
0(
0-
12
#120
b100001010010000101 $
b100001010010000101 8
1(
1-
#125
b100 9
0(
0-
b0 *
b0 3
b1 ,
02
#130
b111 %
b111 6
1<
1(
1-
b1010 .
b1010 4
#135
0;
0(
0-
12
#140
b0 %
b0 6
0<
b10 )
b10 7
1(
1-
#145
b101 9
0(
0-
02
#150
1(
1-
b10100 .
b10100 4
#155
1;
0(
0-
12
#160
b100001010001000101 $
b100001010001000101 8
1(
1-
#165
b110 9
0(
0-
b10100000000000 *
b10100000000000 3
02
#170
b111 %
b111 6
1<
1(
1-
b1010 .
b1010 4
#175
0;
0(
0-
12
#180
b0 %
b0 6
0<
b11 )
b11 7
1(
1-
#185
b111 9
0(
0-
02
#190
1(
1-
b10100 .
b10100 4
#195
1;
0(
0-
12
#200
b100001010010000101 $
b100001010010000101 8
1(
1-
#205
b1000 9
0(
0-
b0 *
b0 3
b10 ,
02
#210
b111 %
b111 6
1<
1(
1-
b1010 .
b1010 4
#215
0;
0(
0-
12
#220
b0 %
b0 6
0<
b100 )
b100 7
1(
1-
#225
b1001 9
0(
0-
02
#230
1(
1-
b10100 .
b10100 4
#235
1;
0(
0-
12
#240
b100001010001000101 $
b100001010001000101 8
1(
1-
#245
b1010 9
0(
0-
b10100000000000 *
b10100000000000 3
02
#250
b111 %
b111 6
1<
1(
1-
b1010 .
b1010 4
#255
0;
0(
0-
12
#260
b0 %
b0 6
0<
b101 )
b101 7
1(
1-
#265
b1011 9
0(
0-
02
#270
1(
1-
b10100 .
b10100 4
#275
1;
0(
0-
12
#280
b100001010010000101 $
b100001010010000101 8
1(
1-
#285
b1100 9
0(
0-
b0 *
b0 3
b11 ,
02
#290
b111 %
b111 6
1<
1(
1-
b1010 .
b1010 4
#295
0;
0(
0-
12
#300
b0 %
b0 6
0<
b110 )
b110 7
1(
1-
#305
b1101 9
0(
0-
02
#310
1(
1-
b10100 .
b10100 4
#315
1;
0(
0-
12
#320
b100001010001000101 $
b100001010001000101 8
1(
1-
#325
b1110 9
0(
0-
b10100000000000 *
b10100000000000 3
02
#330
b111 %
b111 6
1<
1(
1-
b1010 .
b1010 4
#335
0;
0(
0-
12
#340
b0 %
b0 6
0<
b111 )
b111 7
1(
1-
#345
b1111 9
0(
0-
02
#350
1(
1-
b10100 .
b10100 4
#355
1;
0(
0-
12
#360
b100001010010000101 $
b100001010010000101 8
1(
1-
#365
b10000 9
0(
0-
b100 ,
02
#370
b111 %
b111 6
1<
1(
1-
#375
0(
0-
#380
b1000 )
b1000 7
1(
1-
#385
0(
0-
#390
b1001 )
b1001 7
1(
1-
#395
0(
0-
#400
b1010 )
b1010 7
1(
1-
